tableau_to_sqlite/__init__.py
tableau_to_sqlite/cli.py
tableau_to_sqlite-0.2.1.dist-info/LICENSE
tableau_to_sqlite-0.2.1.dist-info/METADATA
tableau_to_sqlite-0.2.1.dist-info/WHEEL
tableau_to_sqlite-0.2.1.dist-info/entry_points.txt
tableau_to_sqlite-0.2.1.dist-info/top_level.txt
tableau_to_sqlite-0.2.1.dist-info/RECORD
