Metadata-Version: 2.1
Name: tableau-to-sqlite
Version: 0.2.1
Summary: Fetch data from Tableau into a SQLite database
Home-page: https://github.com/simonw/tableau-to-sqlite
Author: Simon Willison
License: Apache License, Version 2.0
Project-URL: Issues, https://github.com/simonw/tableau-to-sqlite/issues
Project-URL: CI, https://github.com/simonw/tableau-to-sqlite/actions
Project-URL: Changelog, https://github.com/simonw/tableau-to-sqlite/releases
Platform: UNKNOWN
Requires-Python: >=3.6
Requires-Dist: click
Requires-Dist: TableauScraper (==0.1.2)
Provides-Extra: test
Requires-Dist: pytest ; extra == 'test'
Requires-Dist: vcrpy ; extra == 'test'
